setup.cfg
setup.py
backend/__init__.py
backend.egg-info/PKG-INFO
backend.egg-info/SOURCES.txt
backend.egg-info/dependency_links.txt
backend.egg-info/entry_points.txt
backend.egg-info/top_level.txt
backend.egg-info/zip-safe
backend/fs/__init__.py
backend/fs/models.py
backend/fs/views.py
backend/util/__init__.py
backend/util/settings_context_processor.py
backend/util/views.py
backend/util/templatetags/__init__.py
backend/util/templatetags/utils.py