Metadata-Version: 1.0
Name: backend
Version: 0.2.1
Summary: Backend Utility Tools
Home-page: http://vibhaj.com/
Author: Vibhaj Rajan
Author-email: vibhaj8@gmail.com
License: MIT
Keywords: django backend
Platform: UNKNOWN
